yapeco/__init__.py
yapeco-0.1.5.dist-info/METADATA
yapeco-0.1.5.dist-info/WHEEL
yapeco-0.1.5.dist-info/RECORD
