Metadata-Version: 2.3
Name: yapeco
Version: 0.1.5
Summary: Yet Another Python Envvar Config Object
License: AGPL-3.0-or-later
Keywords: python,config,environment,dotenv,variables
Author: Michael Lisano
Author-email: mlisano@protonmail.com
Requires-Python: >=3.8,<4.0
Classifier: License :: OSI Approved :: GNU Affero General Public License v3 or later (AGPLv3+)
Classifier: Programming Language :: Python :: 3
Classifier: Programming Language :: Python :: 3.8
Classifier: Programming Language :: Python :: 3.9
Classifier: Programming Language :: Python :: 3.10
Classifier: Programming Language :: Python :: 3.11
Classifier: Programming Language :: Python :: 3.12
Classifier: Programming Language :: Python :: 3.13
Classifier: Topic :: Software Development :: Libraries :: Python Modules
Project-URL: Repository, https://github.com/turtlebasket/yapeco
